[{"__type__":"cc.SpriteFrame","content":{"name":"game-export","texture":"d5I6nUazhJaaTuOkDgN31k","rect":[0,0,394,511],"offset":[-59,0.5],"originalSize":[512,512],"capInsets":[0,0,0,0]}},{"__type__":"cc.BitmapFont","_name":"game-export","spriteFrame":{"__uuid__":"d7k8UnnNRKmLl2ZzzVAUHZ"},"fontSize":32,"_fntConfig":{"commonHeight":50,"fontSize":32,"atlasName":"game-export.png","fontDefDictionary":{"9":{"rect":{"x":0,"y":0,"width":0,"height":0},"xOffset":0,"yOffset":0,"xAdvance":35},"32":{"rect":{"x":0,"y":0,"width":0,"height":0},"xOffset":0,"yOffset":0,"xAdvance":7},"33":{"rect":{"x":379,"y":0,"width":15,"height":29},"xOffset":0,"yOffset":21,"xAdvance":16},"35":{"rect":{"x":313,"y":183,"width":24,"height":29},"xOffset":0,"yOffset":21,"xAdvance":25},"36":{"rect":{"x":262,"y":0,"width":25,"height":34},"xOffset":0,"yOffset":18,"xAdvance":26},"37":{"rect":{"x":0,"y":66,"width":34,"height":31},"xOffset":0,"yOffset":20,"xAdvance":35},"38":{"rect":{"x":126,"y":94,"width":28,"height":30},"xOffset":0,"yOffset":20,"xAdvance":29},"40":{"rect":{"x":361,"y":457,"width":17,"height":35},"xOffset":0,"yOffset":20,"xAdvance":18},"41":{"rect":{"x":361,"y":57,"width":18,"height":35},"xOffset":0,"yOffset":20,"xAdvance":19},"42":{"rect":{"x":286,"y":492,"width":20,"height":19},"xOffset":0,"yOffset":21,"xAdvance":21},"43":{"rect":{"x":337,"y":330,"width":24,"height":24},"xOffset":0,"yOffset":26,"xAdvance":25},"44":{"rect":{"x":362,"y":37,"width":16,"height":19},"xOffset":0,"yOffset":35,"xAdvance":17},"45":{"rect":{"x":125,"y":229,"width":19,"height":15},"xOffset":0,"yOffset":30,"xAdvance":20},"46":{"rect":{"x":153,"y":453,"width":16,"height":15},"xOffset":0,"yOffset":35,"xAdvance":17},"47":{"rect":{"x":338,"y":57,"width":22,"height":31},"xOffset":0,"yOffset":20,"xAdvance":23},"48":{"rect":{"x":261,"y":98,"width":25,"height":29},"xOffset":0,"yOffset":21,"xAdvance":26},"49":{"rect":{"x":338,"y":218,"width":20,"height":29},"xOffset":0,"yOffset":21,"xAdvance":21},"50":{"rect":{"x":312,"y":425,"width":24,"height":29},"xOffset":0,"yOffset":21,"xAdvance":25},"51":{"rect":{"x":287,"y":238,"width":25,"height":29},"xOffset":0,"yOffset":21,"xAdvance":26},"52":{"rect":{"x":286,"y":397,"width":25,"height":29},"xOffset":0,"yOffset":21,"xAdvance":26},"53":{"rect":{"x":286,"y":367,"width":25,"height":29},"xOffset":0,"yOffset":21,"xAdvance":26},"54":{"rect":{"x":261,"y":128,"width":25,"height":29},"xOffset":0,"yOffset":21,"xAdvance":26},"55":{"rect":{"x":313,"y":213,"width":24,"height":29},"xOffset":0,"yOffset":21,"xAdvance":25},"56":{"rect":{"x":313,"y":122,"width":24,"height":29},"xOffset":0,"yOffset":21,"xAdvance":25},"57":{"rect":{"x":235,"y":165,"width":25,"height":29},"xOffset":0,"yOffset":21,"xAdvance":26},"58":{"rect":{"x":360,"y":129,"width":16,"height":24},"xOffset":0,"yOffset":26,"xAdvance":17},"59":{"rect":{"x":379,"y":418,"width":15,"height":28},"xOffset":0,"yOffset":26,"xAdvance":16},"60":{"rect":{"x":287,"y":298,"width":25,"height":24},"xOffset":0,"yOffset":26,"xAdvance":26},"61":{"rect":{"x":93,"y":488,"width":25,"height":20},"xOffset":0,"yOffset":28,"xAdvance":26},"62":{"rect":{"x":287,"y":135,"width":25,"height":24},"xOffset":0,"yOffset":26,"xAdvance":26},"63":{"rect":{"x":313,"y":152,"width":24,"height":30},"xOffset":0,"yOffset":20,"xAdvance":25},"64":{"rect":{"x":34,"y":242,"width":30,"height":31},"xOffset":0,"yOffset":20,"xAdvance":31},"65":{"rect":{"x":123,"y":402,"width":29,"height":29},"xOffset":0,"yOffset":21,"xAdvance":30},"66":{"rect":{"x":153,"y":326,"width":27,"height":29},"xOffset":0,"yOffset":21,"xAdvance":28},"67":{"rect":{"x":123,"y":469,"width":28,"height":31},"xOffset":0,"yOffset":20,"xAdvance":29},"68":{"rect":{"x":153,"y":356,"width":27,"height":29},"xOffset":0,"yOffset":21,"xAdvance":28},"69":{"rect":{"x":287,"y":268,"width":25,"height":29},"xOffset":0,"yOffset":21,"xAdvance":26},"70":{"rect":{"x":261,"y":158,"width":25,"height":29},"xOffset":0,"yOffset":21,"xAdvance":26},"71":{"rect":{"x":64,"y":341,"width":29,"height":31},"xOffset":0,"yOffset":20,"xAdvance":30},"72":{"rect":{"x":154,"y":155,"width":27,"height":29},"xOffset":0,"yOffset":21,"xAdvance":28},"73":{"rect":{"x":379,"y":354,"width":15,"height":29},"xOffset":0,"yOffset":21,"xAdvance":16},"74":{"rect":{"x":337,"y":380,"width":23,"height":30},"xOffset":0,"yOffset":21,"xAdvance":24},"75":{"rect":{"x":125,"y":169,"width":28,"height":29},"xOffset":0,"yOffset":20,"xAdvance":29},"76":{"rect":{"x":286,"y":427,"width":25,"height":29},"xOffset":0,"yOffset":20,"xAdvance":26},"77":{"rect":{"x":34,"y":212,"width":30,"height":29},"xOffset":0,"yOffset":20,"xAdvance":31},"78":{"rect":{"x":182,"y":132,"width":26,"height":29},"xOffset":0,"yOffset":20,"xAdvance":27},"79":{"rect":{"x":64,"y":309,"width":29,"height":31},"xOffset":0,"yOffset":19,"xAdvance":30},"80":{"rect":{"x":181,"y":359,"width":26,"height":29},"xOffset":0,"yOffset":20,"xAdvance":27},"81":{"rect":{"x":32,"y":456,"width":30,"height":32},"xOffset":0,"yOffset":19,"xAdvance":31},"82":{"rect":{"x":181,"y":296,"width":27,"height":29},"xOffset":0,"yOffset":20,"xAdvance":28},"83":{"rect":{"x":181,"y":389,"width":26,"height":31},"xOffset":0,"yOffset":19,"xAdvance":27},"84":{"rect":{"x":181,"y":266,"width":27,"height":29},"xOffset":0,"yOffset":20,"xAdvance":28},"85":{"rect":{"x":183,"y":38,"width":26,"height":30},"xOffset":0,"yOffset":20,"xAdvance":27},"86":{"rect":{"x":154,"y":125,"width":27,"height":29},"xOffset":0,"yOffset":21,"xAdvance":28},"87":{"rect":{"x":0,"y":0,"width":35,"height":29},"xOffset":0,"yOffset":21,"xAdvance":36},"88":{"rect":{"x":153,"y":423,"width":27,"height":29},"xOffset":0,"yOffset":21,"xAdvance":28},"89":{"rect":{"x":125,"y":199,"width":28,"height":29},"xOffset":0,"yOffset":21,"xAdvance":29},"90":{"rect":{"x":153,"y":296,"width":27,"height":29},"xOffset":0,"yOffset":21,"xAdvance":28},"91":{"rect":{"x":362,"y":318,"width":17,"height":35},"xOffset":0,"yOffset":20,"xAdvance":18},"92":{"rect":{"x":338,"y":89,"width":22,"height":31},"xOffset":0,"yOffset":20,"xAdvance":23},"93":{"rect":{"x":361,"y":93,"width":18,"height":35},"xOffset":0,"yOffset":20,"xAdvance":19},"94":{"rect":{"x":208,"y":489,"width":22,"height":21},"xOffset":0,"yOffset":21,"xAdvance":23},"95":{"rect":{"x":31,"y":492,"width":25,"height":13},"xOffset":0,"yOffset":40,"xAdvance":26},"96":{"rect":{"x":181,"y":495,"width":18,"height":16},"xOffset":0,"yOffset":20,"xAdvance":19},"97":{"rect":{"x":209,"y":332,"width":25,"height":25},"xOffset":0,"yOffset":25,"xAdvance":26},"98":{"rect":{"x":234,"y":426,"width":25,"height":29},"xOffset":0,"yOffset":21,"xAdvance":26},"99":{"rect":{"x":65,"y":246,"width":25,"height":25},"xOffset":0,"yOffset":25,"xAdvance":26},"100":{"rect":{"x":234,"y":396,"width":25,"height":29},"xOffset":0,"yOffset":21,"xAdvance":26},"101":{"rect":{"x":312,"y":485,"width":24,"height":25},"xOffset":0,"yOffset":25,"xAdvance":25},"102":{"rect":{"x":359,"y":156,"width":20,"height":29},"xOffset":0,"yOffset":21,"xAdvance":21},"103":{"rect":{"x":210,"y":31,"width":25,"height":30},"xOffset":0,"yOffset":25,"xAdvance":26},"104":{"rect":{"x":337,"y":442,"width":23,"height":29},"xOffset":0,"yOffset":21,"xAdvance":24},"105":{"rect":{"x":379,"y":447,"width":15,"height":29},"xOffset":0,"yOffset":21,"xAdvance":16},"106":{"rect":{"x":361,"y":391,"width":17,"height":34},"xOffset":0,"yOffset":21,"xAdvance":18},"107":{"rect":{"x":337,"y":300,"width":24,"height":29},"xOffset":0,"yOffset":21,"xAdvance":25},"108":{"rect":{"x":379,"y":220,"width":15,"height":29},"xOffset":0,"yOffset":21,"xAdvance":16},"109":{"rect":{"x":0,"y":457,"width":31,"height":25},"xOffset":0,"yOffset":25,"xAdvance":32},"110":{"rect":{"x":338,"y":31,"width":23,"height":25},"xOffset":0,"yOffset":25,"xAdvance":24},"111":{"rect":{"x":155,"y":99,"width":25,"height":25},"xOffset":0,"yOffset":25,"xAdvance":26},"112":{"rect":{"x":287,"y":35,"width":25,"height":30},"xOffset":0,"yOffset":25,"xAdvance":26},"113":{"rect":{"x":209,"y":301,"width":25,"height":30},"xOffset":0,"yOffset":25,"xAdvance":26},"114":{"rect":{"x":338,"y":192,"width":20,"height":25},"xOffset":0,"yOffset":25,"xAdvance":21},"115":{"rect":{"x":313,"y":243,"width":24,"height":25},"xOffset":0,"yOffset":25,"xAdvance":25},"116":{"rect":{"x":359,"y":222,"width":19,"height":28},"xOffset":0,"yOffset":22,"xAdvance":20},"117":{"rect":{"x":261,"y":367,"width":24,"height":24},"xOffset":0,"yOffset":26,"xAdvance":25},"118":{"rect":{"x":236,"y":35,"width":24,"height":24},"xOffset":0,"yOffset":26,"xAdvance":25},"119":{"rect":{"x":0,"y":483,"width":30,"height":24},"xOffset":0,"yOffset":26,"xAdvance":31},"120":{"rect":{"x":260,"y":487,"width":25,"height":24},"xOffset":0,"yOffset":26,"xAdvance":26},"121":{"rect":{"x":313,"y":30,"width":24,"height":29},"xOffset":0,"yOffset":26,"xAdvance":25},"122":{"rect":{"x":337,"y":355,"width":23,"height":24},"xOffset":0,"yOffset":26,"xAdvance":24},"123":{"rect":{"x":338,"y":156,"width":20,"height":35},"xOffset":0,"yOffset":20,"xAdvance":21},"124":{"rect":{"x":380,"y":30,"width":14,"height":36},"xOffset":0,"yOffset":19,"xAdvance":15},"125":{"rect":{"x":359,"y":186,"width":19,"height":35},"xOffset":0,"yOffset":20,"xAdvance":20},"126":{"rect":{"x":57,"y":492,"width":23,"height":16},"xOffset":0,"yOffset":30,"xAdvance":24},"192":{"rect":{"x":96,"y":0,"width":29,"height":35},"xOffset":0,"yOffset":15,"xAdvance":30},"193":{"rect":{"x":96,"y":99,"width":29,"height":35},"xOffset":0,"yOffset":15,"xAdvance":30},"194":{"rect":{"x":66,"y":74,"width":29,"height":35},"xOffset":0,"yOffset":15,"xAdvance":30},"195":{"rect":{"x":95,"y":177,"width":29,"height":34},"xOffset":0,"yOffset":16,"xAdvance":30},"200":{"rect":{"x":261,"y":261,"width":25,"height":35},"xOffset":0,"yOffset":15,"xAdvance":26},"201":{"rect":{"x":261,"y":188,"width":25,"height":35},"xOffset":0,"yOffset":15,"xAdvance":26},"202":{"rect":{"x":261,"y":297,"width":25,"height":35},"xOffset":0,"yOffset":15,"xAdvance":26},"204":{"rect":{"x":361,"y":355,"width":17,"height":35},"xOffset":0,"yOffset":14,"xAdvance":18},"205":{"rect":{"x":359,"y":251,"width":18,"height":35},"xOffset":0,"yOffset":14,"xAdvance":19},"210":{"rect":{"x":65,"y":141,"width":29,"height":36},"xOffset":0,"yOffset":14,"xAdvance":30},"211":{"rect":{"x":63,"y":417,"width":29,"height":36},"xOffset":0,"yOffset":14,"xAdvance":30},"212":{"rect":{"x":35,"y":104,"width":30,"height":36},"xOffset":0,"yOffset":14,"xAdvance":31},"213":{"rect":{"x":35,"y":68,"width":30,"height":35},"xOffset":0,"yOffset":15,"xAdvance":31},"217":{"rect":{"x":182,"y":195,"width":26,"height":36},"xOffset":0,"yOffset":14,"xAdvance":27},"218":{"rect":{"x":208,"y":359,"width":26,"height":36},"xOffset":0,"yOffset":14,"xAdvance":27},"221":{"rect":{"x":152,"y":469,"width":28,"height":35},"xOffset":0,"yOffset":15,"xAdvance":29},"224":{"rect":{"x":260,"y":456,"width":25,"height":30},"xOffset":0,"yOffset":20,"xAdvance":26},"225":{"rect":{"x":261,"y":67,"width":25,"height":30},"xOffset":0,"yOffset":20,"xAdvance":26},"226":{"rect":{"x":235,"y":195,"width":25,"height":30},"xOffset":0,"yOffset":20,"xAdvance":26},"227":{"rect":{"x":260,"y":396,"width":25,"height":29},"xOffset":0,"yOffset":21,"xAdvance":26},"232":{"rect":{"x":209,"y":238,"width":25,"height":30},"xOffset":0,"yOffset":20,"xAdvance":26},"233":{"rect":{"x":313,"y":269,"width":24,"height":30},"xOffset":0,"yOffset":20,"xAdvance":25},"234":{"rect":{"x":312,"y":394,"width":24,"height":30},"xOffset":0,"yOffset":20,"xAdvance":25},"236":{"rect":{"x":362,"y":287,"width":17,"height":30},"xOffset":0,"yOffset":20,"xAdvance":18},"237":{"rect":{"x":361,"y":426,"width":17,"height":30},"xOffset":0,"yOffset":20,"xAdvance":18},"242":{"rect":{"x":208,"y":396,"width":25,"height":30},"xOffset":0,"yOffset":20,"xAdvance":26},"243":{"rect":{"x":210,"y":0,"width":25,"height":30},"xOffset":0,"yOffset":20,"xAdvance":26},"244":{"rect":{"x":209,"y":103,"width":25,"height":30},"xOffset":0,"yOffset":20,"xAdvance":26},"245":{"rect":{"x":183,"y":69,"width":25,"height":29},"xOffset":0,"yOffset":21,"xAdvance":26},"249":{"rect":{"x":337,"y":411,"width":23,"height":30},"xOffset":0,"yOffset":20,"xAdvance":24},"250":{"rect":{"x":338,"y":0,"width":23,"height":30},"xOffset":0,"yOffset":20,"xAdvance":24},"253":{"rect":{"x":312,"y":323,"width":24,"height":35},"xOffset":0,"yOffset":20,"xAdvance":25},"258":{"rect":{"x":95,"y":141,"width":29,"height":35},"xOffset":0,"yOffset":15,"xAdvance":30},"259":{"rect":{"x":235,"y":365,"width":25,"height":30},"xOffset":0,"yOffset":20,"xAdvance":26},"272":{"rect":{"x":35,"y":141,"width":29,"height":29},"xOffset":0,"yOffset":21,"xAdvance":30},"273":{"rect":{"x":153,"y":266,"width":27,"height":29},"xOffset":0,"yOffset":21,"xAdvance":28},"296":{"rect":{"x":338,"y":121,"width":21,"height":34},"xOffset":0,"yOffset":15,"xAdvance":22},"297":{"rect":{"x":338,"y":248,"width":20,"height":29},"xOffset":0,"yOffset":21,"xAdvance":21},"360":{"rect":{"x":154,"y":185,"width":27,"height":35},"xOffset":0,"yOffset":16,"xAdvance":28},"361":{"rect":{"x":313,"y":60,"width":24,"height":29},"xOffset":0,"yOffset":21,"xAdvance":25},"416":{"rect":{"x":0,"y":171,"width":33,"height":31},"xOffset":0,"yOffset":19,"xAdvance":34},"417":{"rect":{"x":33,"y":355,"width":29,"height":25},"xOffset":0,"yOffset":25,"xAdvance":30},"431":{"rect":{"x":0,"y":351,"width":32,"height":30},"xOffset":0,"yOffset":21,"xAdvance":33},"432":{"rect":{"x":124,"y":376,"width":28,"height":25},"xOffset":0,"yOffset":25,"xAdvance":29},"7840":{"rect":{"x":95,"y":212,"width":29,"height":33},"xOffset":0,"yOffset":21,"xAdvance":30},"7841":{"rect":{"x":260,"y":426,"width":25,"height":29},"xOffset":0,"yOffset":25,"xAdvance":26},"7842":{"rect":{"x":123,"y":432,"width":29,"height":36},"xOffset":0,"yOffset":14,"xAdvance":30},"7843":{"rect":{"x":261,"y":35,"width":25,"height":31},"xOffset":0,"yOffset":19,"xAdvance":26},"7844":{"rect":{"x":66,"y":37,"width":29,"height":36},"xOffset":0,"yOffset":14,"xAdvance":30},"7845":{"rect":{"x":182,"y":232,"width":26,"height":32},"xOffset":0,"yOffset":18,"xAdvance":27},"7846":{"rect":{"x":64,"y":373,"width":29,"height":36},"xOffset":0,"yOffset":14,"xAdvance":30},"7847":{"rect":{"x":182,"y":162,"width":26,"height":32},"xOffset":0,"yOffset":18,"xAdvance":27},"7848":{"rect":{"x":66,"y":0,"width":29,"height":36},"xOffset":0,"yOffset":14,"xAdvance":30},"7849":{"rect":{"x":235,"y":131,"width":25,"height":33},"xOffset":0,"yOffset":17,"xAdvance":26},"7850":{"rect":{"x":94,"y":324,"width":29,"height":38},"xOffset":0,"yOffset":12,"xAdvance":30},"7851":{"rect":{"x":234,"y":456,"width":25,"height":34},"xOffset":0,"yOffset":16,"xAdvance":26},"7852":{"rect":{"x":94,"y":285,"width":29,"height":38},"xOffset":0,"yOffset":16,"xAdvance":30},"7853":{"rect":{"x":235,"y":62,"width":25,"height":34},"xOffset":0,"yOffset":20,"xAdvance":26},"7854":{"rect":{"x":94,"y":363,"width":29,"height":38},"xOffset":0,"yOffset":12,"xAdvance":30},"7855":{"rect":{"x":236,"y":0,"width":25,"height":34},"xOffset":0,"yOffset":16,"xAdvance":26},"7856":{"rect":{"x":94,"y":246,"width":29,"height":38},"xOffset":0,"yOffset":12,"xAdvance":30},"7857":{"rect":{"x":235,"y":296,"width":25,"height":34},"xOffset":0,"yOffset":16,"xAdvance":26},"7858":{"rect":{"x":65,"y":178,"width":29,"height":36},"xOffset":0,"yOffset":14,"xAdvance":30},"7859":{"rect":{"x":235,"y":331,"width":25,"height":33},"xOffset":0,"yOffset":17,"xAdvance":26},"7860":{"rect":{"x":93,"y":410,"width":29,"height":38},"xOffset":0,"yOffset":12,"xAdvance":30},"7861":{"rect":{"x":235,"y":226,"width":25,"height":34},"xOffset":0,"yOffset":16,"xAdvance":26},"7862":{"rect":{"x":93,"y":449,"width":29,"height":38},"xOffset":0,"yOffset":16,"xAdvance":30},"7863":{"rect":{"x":235,"y":261,"width":25,"height":34},"xOffset":0,"yOffset":20,"xAdvance":26},"7864":{"rect":{"x":287,"y":101,"width":25,"height":33},"xOffset":0,"yOffset":21,"xAdvance":26},"7865":{"rect":{"x":313,"y":0,"width":24,"height":29},"xOffset":0,"yOffset":25,"xAdvance":25},"7866":{"rect":{"x":261,"y":224,"width":25,"height":36},"xOffset":0,"yOffset":14,"xAdvance":26},"7867":{"rect":{"x":209,"y":269,"width":25,"height":31},"xOffset":0,"yOffset":19,"xAdvance":26},"7868":{"rect":{"x":261,"y":333,"width":25,"height":33},"xOffset":0,"yOffset":17,"xAdvance":26},"7869":{"rect":{"x":312,"y":455,"width":24,"height":29},"xOffset":0,"yOffset":21,"xAdvance":25},"7870":{"rect":{"x":153,"y":386,"width":27,"height":36},"xOffset":0,"yOffset":14,"xAdvance":28},"7871":{"rect":{"x":155,"y":32,"width":27,"height":32},"xOffset":0,"yOffset":18,"xAdvance":28},"7872":{"rect":{"x":181,"y":458,"width":26,"height":36},"xOffset":0,"yOffset":14,"xAdvance":27},"7873":{"rect":{"x":182,"y":99,"width":26,"height":32},"xOffset":0,"yOffset":18,"xAdvance":27},"7874":{"rect":{"x":181,"y":421,"width":26,"height":36},"xOffset":0,"yOffset":14,"xAdvance":27},"7875":{"rect":{"x":209,"y":69,"width":25,"height":33},"xOffset":0,"yOffset":17,"xAdvance":26},"7876":{"rect":{"x":287,"y":160,"width":25,"height":38},"xOffset":0,"yOffset":12,"xAdvance":26},"7877":{"rect":{"x":288,"y":0,"width":24,"height":34},"xOffset":0,"yOffset":16,"xAdvance":25},"7878":{"rect":{"x":287,"y":199,"width":25,"height":38},"xOffset":0,"yOffset":16,"xAdvance":26},"7879":{"rect":{"x":312,"y":359,"width":24,"height":34},"xOffset":0,"yOffset":20,"xAdvance":25},"7880":{"rect":{"x":362,"y":0,"width":16,"height":36},"xOffset":0,"yOffset":13,"xAdvance":17},"7881":{"rect":{"x":378,"y":251,"width":16,"height":31},"xOffset":0,"yOffset":19,"xAdvance":17},"7882":{"rect":{"x":379,"y":186,"width":15,"height":33},"xOffset":0,"yOffset":20,"xAdvance":16},"7883":{"rect":{"x":379,"y":384,"width":15,"height":33},"xOffset":0,"yOffset":21,"xAdvance":16},"7884":{"rect":{"x":64,"y":274,"width":29,"height":34},"xOffset":0,"yOffset":19,"xAdvance":30},"7885":{"rect":{"x":208,"y":459,"width":25,"height":29},"xOffset":0,"yOffset":25,"xAdvance":26},"7886":{"rect":{"x":63,"y":454,"width":29,"height":37},"xOffset":0,"yOffset":13,"xAdvance":30},"7887":{"rect":{"x":208,"y":427,"width":25,"height":31},"xOffset":0,"yOffset":19,"xAdvance":26},"7888":{"rect":{"x":35,"y":30,"width":30,"height":37},"xOffset":0,"yOffset":13,"xAdvance":31},"7889":{"rect":{"x":155,"y":0,"width":27,"height":31},"xOffset":0,"yOffset":19,"xAdvance":28},"7890":{"rect":{"x":33,"y":278,"width":30,"height":38},"xOffset":0,"yOffset":12,"xAdvance":31},"7891":{"rect":{"x":181,"y":326,"width":27,"height":32},"xOffset":0,"yOffset":18,"xAdvance":28},"7892":{"rect":{"x":33,"y":317,"width":30,"height":37},"xOffset":0,"yOffset":13,"xAdvance":31},"7893":{"rect":{"x":209,"y":134,"width":25,"height":33},"xOffset":0,"yOffset":17,"xAdvance":26},"7894":{"rect":{"x":34,"y":171,"width":30,"height":40},"xOffset":0,"yOffset":10,"xAdvance":31},"7895":{"rect":{"x":209,"y":203,"width":25,"height":34},"xOffset":0,"yOffset":16,"xAdvance":26},"7896":{"rect":{"x":32,"y":417,"width":30,"height":38},"xOffset":0,"yOffset":15,"xAdvance":31},"7897":{"rect":{"x":209,"y":168,"width":25,"height":34},"xOffset":0,"yOffset":20,"xAdvance":26},"7898":{"rect":{"x":0,"y":98,"width":34,"height":36},"xOffset":0,"yOffset":14,"xAdvance":35},"7899":{"rect":{"x":96,"y":36,"width":29,"height":30},"xOffset":0,"yOffset":20,"xAdvance":30},"7900":{"rect":{"x":0,"y":203,"width":33,"height":36},"xOffset":0,"yOffset":14,"xAdvance":34},"7901":{"rect":{"x":66,"y":110,"width":29,"height":30},"xOffset":0,"yOffset":20,"xAdvance":30},"7902":{"rect":{"x":0,"y":240,"width":33,"height":37},"xOffset":0,"yOffset":13,"xAdvance":34},"7903":{"rect":{"x":96,"y":67,"width":29,"height":31},"xOffset":0,"yOffset":19,"xAdvance":30},"7904":{"rect":{"x":0,"y":135,"width":34,"height":35},"xOffset":0,"yOffset":15,"xAdvance":35},"7905":{"rect":{"x":36,"y":0,"width":29,"height":29},"xOffset":0,"yOffset":21,"xAdvance":30},"7906":{"rect":{"x":0,"y":30,"width":34,"height":35},"xOffset":0,"yOffset":19,"xAdvance":35},"7907":{"rect":{"x":65,"y":215,"width":29,"height":30},"xOffset":0,"yOffset":25,"xAdvance":30},"7908":{"rect":{"x":155,"y":65,"width":27,"height":33},"xOffset":0,"yOffset":21,"xAdvance":28},"7909":{"rect":{"x":337,"y":472,"width":23,"height":28},"xOffset":0,"yOffset":26,"xAdvance":24},"7910":{"rect":{"x":183,"y":0,"width":26,"height":37},"xOffset":0,"yOffset":13,"xAdvance":27},"7911":{"rect":{"x":313,"y":90,"width":24,"height":31},"xOffset":0,"yOffset":19,"xAdvance":25},"7912":{"rect":{"x":0,"y":420,"width":31,"height":36},"xOffset":0,"yOffset":15,"xAdvance":32},"7913":{"rect":{"x":126,"y":0,"width":28,"height":30},"xOffset":0,"yOffset":20,"xAdvance":29},"7914":{"rect":{"x":0,"y":314,"width":32,"height":36},"xOffset":0,"yOffset":15,"xAdvance":33},"7915":{"rect":{"x":126,"y":31,"width":28,"height":30},"xOffset":0,"yOffset":20,"xAdvance":29},"7916":{"rect":{"x":0,"y":382,"width":31,"height":37},"xOffset":0,"yOffset":14,"xAdvance":32},"7917":{"rect":{"x":126,"y":62,"width":28,"height":31},"xOffset":0,"yOffset":19,"xAdvance":29},"7918":{"rect":{"x":0,"y":278,"width":32,"height":35},"xOffset":0,"yOffset":16,"xAdvance":33},"7919":{"rect":{"x":124,"y":277,"width":28,"height":29},"xOffset":0,"yOffset":21,"xAdvance":29},"7920":{"rect":{"x":32,"y":382,"width":31,"height":34},"xOffset":0,"yOffset":21,"xAdvance":32},"7921":{"rect":{"x":124,"y":246,"width":28,"height":30},"xOffset":0,"yOffset":25,"xAdvance":29},"7922":{"rect":{"x":124,"y":307,"width":28,"height":34},"xOffset":0,"yOffset":16,"xAdvance":29},"7923":{"rect":{"x":286,"y":457,"width":25,"height":34},"xOffset":0,"yOffset":21,"xAdvance":26},"7924":{"rect":{"x":124,"y":342,"width":28,"height":33},"xOffset":0,"yOffset":21,"xAdvance":29},"7925":{"rect":{"x":235,"y":97,"width":25,"height":33},"xOffset":0,"yOffset":26,"xAdvance":26},"7926":{"rect":{"x":153,"y":229,"width":28,"height":36},"xOffset":0,"yOffset":14,"xAdvance":29},"7927":{"rect":{"x":287,"y":323,"width":24,"height":36},"xOffset":0,"yOffset":19,"xAdvance":25},"7928":{"rect":{"x":125,"y":135,"width":28,"height":33},"xOffset":0,"yOffset":17,"xAdvance":29},"7929":{"rect":{"x":287,"y":66,"width":25,"height":34},"xOffset":0,"yOffset":21,"xAdvance":26},"8217":{"rect":{"x":361,"y":493,"width":15,"height":18},"xOffset":0,"yOffset":21,"xAdvance":16},"8221":{"rect":{"x":231,"y":491,"width":20,"height":18},"xOffset":0,"yOffset":21,"xAdvance":21}},"kerningDict":{}}}]