[{"__type__":"cc.BitmapFont","_name":"tien-export","spriteFrame":{"__uuid__":"d2QX9ROutItIQX2gPLEcG2"},"fontSize":32,"_fntConfig":{"commonHeight":50,"fontSize":32,"atlasName":"tien-export.png","fontDefDictionary":{"9":{"rect":{"x":0,"y":0,"width":0,"height":0},"xOffset":0,"yOffset":0,"xAdvance":35},"32":{"rect":{"x":0,"y":0,"width":0,"height":0},"xOffset":0,"yOffset":0,"xAdvance":7},"44":{"rect":{"x":0,"y":107,"width":9,"height":14},"xOffset":0,"yOffset":41,"xAdvance":10},"46":{"rect":{"x":10,"y":107,"width":9,"height":9},"xOffset":0,"yOffset":41,"xAdvance":10},"48":{"rect":{"x":22,"y":79,"width":21,"height":27},"xOffset":0,"yOffset":24,"xAdvance":22},"49":{"rect":{"x":28,"y":0,"width":13,"height":25},"xOffset":0,"yOffset":25,"xAdvance":14},"50":{"rect":{"x":45,"y":0,"width":20,"height":26},"xOffset":0,"yOffset":24,"xAdvance":21},"51":{"rect":{"x":45,"y":27,"width":20,"height":27},"xOffset":0,"yOffset":24,"xAdvance":21},"52":{"rect":{"x":23,"y":26,"width":21,"height":25},"xOffset":0,"yOffset":25,"xAdvance":22},"53":{"rect":{"x":23,"y":52,"width":21,"height":26},"xOffset":0,"yOffset":25,"xAdvance":22},"54":{"rect":{"x":0,"y":26,"width":22,"height":26},"xOffset":0,"yOffset":25,"xAdvance":23},"55":{"rect":{"x":65,"y":81,"width":19,"height":25},"xOffset":0,"yOffset":25,"xAdvance":20},"56":{"rect":{"x":44,"y":79,"width":20,"height":27},"xOffset":0,"yOffset":24,"xAdvance":21},"57":{"rect":{"x":0,"y":79,"width":21,"height":26},"xOffset":0,"yOffset":24,"xAdvance":22},"66":{"rect":{"x":65,"y":55,"width":20,"height":25},"xOffset":0,"yOffset":25,"xAdvance":21},"75":{"rect":{"x":0,"y":53,"width":22,"height":25},"xOffset":0,"yOffset":25,"xAdvance":23},"77":{"rect":{"x":0,"y":0,"width":27,"height":25},"xOffset":0,"yOffset":25,"xAdvance":28}},"kerningDict":{}}},{"__type__":"cc.SpriteFrame","content":{"name":"tien-export","texture":"403d1KgWBL6KEEkmOhZ9Xz","rect":[0,0,85,121],"offset":[-21.5,3.5],"originalSize":[128,128],"capInsets":[0,0,0,0]}}]