[{"__type__":"cc.SpriteFrame","content":{"name":"p-3","texture":"4bNWVrT2hJm4pGB87KGOKP","rect":[1413,0,51,52],"offset":[0,0],"originalSize":[51,52],"capInsets":[0,0,0,0]}},{"__type__":"cc.SpriteFrame","content":{"name":"tip","texture":"4bNWVrT2hJm4pGB87KGOKP","rect":[1128,0,81,47],"offset":[0,0],"originalSize":[81,47],"capInsets":[0,0,0,0]}},{"__type__":"cc.SpriteFrame","content":{"name":"le","texture":"4bNWVrT2hJm4pGB87KGOKP","rect":[967,55,65,63],"offset":[0,0],"originalSize":[65,63],"capInsets":[0,0,0,0]}},{"__type__":"cc.SpriteFrame","content":{"name":"tai-xiu-bg-2","texture":"4bNWVrT2hJm4pGB87KGOKP","rect":[759,1220,716,210],"offset":[0,0],"originalSize":[716,210],"capInsets":[0,0,0,0]}},{"__type__":"cc.SpriteFrame","content":{"name":"diaNan","texture":"4bNWVrT2hJm4pGB87KGOKP","rect":[1187,295,184,184],"offset":[0,0],"originalSize":[184,184],"capInsets":[0,0,0,0]}},{"__type__":"cc.SpriteFrame","content":{"name":"p-5","texture":"4bNWVrT2hJm4pGB87KGOKP","rect":[1260,0,51,52],"offset":[0,0],"originalSize":[51,52],"capInsets":[0,0,0,0]}},{"__type__":"cc.SpriteFrame","content":{"name":"bg-history","texture":"4bNWVrT2hJm4pGB87KGOKP","rect":[340,1508,686,440],"offset":[0,0],"originalSize":[686,440],"capInsets":[0,0,0,0]}},{"__type__":"cc.SpriteFrame","content":{"name":"p-1","texture":"4bNWVrT2hJm4pGB87KGOKP","rect":[1311,0,51,52],"offset":[0,0],"originalSize":[51,52],"capInsets":[0,0,0,0]}},{"__type__":"cc.SpriteFrame","content":{"name":"bg_number","texture":"4bNWVrT2hJm4pGB87KGOKP","rect":[1515,0,135,55],"offset":[0,0],"originalSize":[135,55],"capInsets":[0,0,0,0]}},{"__type__":"cc.SpriteFrame","content":{"name":"xiu","texture":"4bNWVrT2hJm4pGB87KGOKP","rect":[1678,55,119,85],"offset":[0,0],"originalSize":[119,85],"capInsets":[0,0,0,0]}},{"__type__":"cc.SpriteFrame","content":{"name":"p-4","texture":"4bNWVrT2hJm4pGB87KGOKP","rect":[1209,0,51,52],"offset":[0,0],"originalSize":[51,52],"capInsets":[0,0,0,0]}},{"__type__":"cc.SpriteFrame","content":{"name":"dice_22","texture":"4bNWVrT2hJm4pGB87KGOKP","rect":[0,1220,185,185],"offset":[0,0],"originalSize":[185,185],"capInsets":[0,0,0,0]}},{"__type__":"cc.SpriteFrame","content":{"name":"thongke_xucxac2","texture":"4bNWVrT2hJm4pGB87KGOKP","rect":[48,0,27,27],"offset":[0,0],"originalSize":[27,27],"capInsets":[0,0,0,0]}},{"__type__":"cc.SpriteFrame","content":{"name":"dice_08","texture":"4bNWVrT2hJm4pGB87KGOKP","rect":[1480,665,185,185],"offset":[0,0],"originalSize":[185,185],"capInsets":[0,0,0,0]}},{"__type__":"cc.SpriteFrame","content":{"name":"dice_10","texture":"4bNWVrT2hJm4pGB87KGOKP","rect":[740,665,185,185],"offset":[0,0],"originalSize":[185,185],"capInsets":[0,0,0,0]}},{"__type__":"cc.SpriteFrame","content":{"name":"dice_35","texture":"4bNWVrT2hJm4pGB87KGOKP","rect":[1295,850,185,185],"offset":[0,0],"originalSize":[185,185],"capInsets":[0,0,0,0]}},{"__type__":"cc.SpriteFrame","content":{"name":"tai-xiu-button-nan-off","texture":"4bNWVrT2hJm4pGB87KGOKP","rect":[1600,55,78,82],"offset":[0,0],"originalSize":[78,82],"capInsets":[0,0,0,0]}},{"__type__":"cc.SpriteFrame","content":{"name":"dice_03","texture":"4bNWVrT2hJm4pGB87KGOKP","rect":[0,850,185,185],"offset":[0,0],"originalSize":[185,185],"capInsets":[0,0,0,0]}},{"__type__":"cc.SpriteFrame","content":{"name":"dot","texture":"4bNWVrT2hJm4pGB87KGOKP","rect":[22,0,26,26],"offset":[0,0],"originalSize":[26,26],"capInsets":[0,0,0,0]}},{"__type__":"cc.SpriteFrame","content":{"name":"dice_14","texture":"4bNWVrT2hJm4pGB87KGOKP","rect":[0,665,185,185],"offset":[0,0],"originalSize":[185,185],"capInsets":[0,0,0,0]}},{"__type__":"cc.SpriteFrame","content":{"name":"dice_32","texture":"4bNWVrT2hJm4pGB87KGOKP","rect":[1480,850,185,185],"offset":[0,0],"originalSize":[185,185],"capInsets":[0,0,0,0]}},{"__type__":"cc.SpriteFrame","content":{"name":"thongke_tong","texture":"4bNWVrT2hJm4pGB87KGOKP","rect":[102,0,27,27],"offset":[0,0],"originalSize":[27,27],"capInsets":[0,0,0,0]}},{"__type__":"cc.SpriteFrame","content":{"name":"bg-text","texture":"4bNWVrT2hJm4pGB87KGOKP","rect":[862,0,266,38],"offset":[0,0],"originalSize":[266,38],"capInsets":[0,0,0,0]}},{"__type__":"cc.SpriteFrame","content":{"name":"dice_29","texture":"4bNWVrT2hJm4pGB87KGOKP","rect":[555,850,185,185],"offset":[0,0],"originalSize":[185,185],"capInsets":[0,0,0,0]}},{"__type__":"cc.SpriteFrame","content":{"name":"dice_15","texture":"4bNWVrT2hJm4pGB87KGOKP","rect":[1480,480,185,185],"offset":[0,0],"originalSize":[185,185],"capInsets":[0,0,0,0]}},{"__type__":"cc.SpriteFrame","content":{"name":"dice_05","texture":"4bNWVrT2hJm4pGB87KGOKP","rect":[555,665,185,185],"offset":[0,0],"originalSize":[185,185],"capInsets":[0,0,0,0]}},{"__type__":"cc.SpriteFrame","content":{"name":"dice_16","texture":"4bNWVrT2hJm4pGB87KGOKP","rect":[925,480,185,185],"offset":[0,0],"originalSize":[185,185],"capInsets":[0,0,0,0]}},{"__type__":"cc.SpriteFrame","content":{"name":"thongke_xucxac1","texture":"4bNWVrT2hJm4pGB87KGOKP","rect":[129,0,27,27],"offset":[0,0],"originalSize":[27,27],"capInsets":[0,0,0,0]}},{"__type__":"cc.SpriteFrame","content":{"name":"dot_white","texture":"4bNWVrT2hJm4pGB87KGOKP","rect":[249,0,30,29],"offset":[0,0],"originalSize":[30,29],"capInsets":[0,0,0,0]}},{"__type__":"cc.SpriteFrame","content":{"name":"bg_number_light","texture":"4bNWVrT2hJm4pGB87KGOKP","rect":[1650,0,135,55],"offset":[0,0],"originalSize":[135,55],"capInsets":[0,0,0,0]}},{"__type__":"cc.SpriteFrame","content":{"name":"dice_39","texture":"4bNWVrT2hJm4pGB87KGOKP","rect":[0,480,185,185],"offset":[0,0],"originalSize":[185,185],"capInsets":[0,0,0,0]}},{"__type__":"cc.SpriteFrame","content":{"name":"tai-xiu-bet-bg-2","texture":"4bNWVrT2hJm4pGB87KGOKP","rect":[378,55,230,60],"offset":[0,0],"originalSize":[230,60],"capInsets":[0,0,0,0]}},{"__type__":"cc.SpriteFrame","content":{"name":"dice_17","texture":"4bNWVrT2hJm4pGB87KGOKP","rect":[185,850,185,185],"offset":[0,0],"originalSize":[185,185],"capInsets":[0,0,0,0]}},{"__type__":"cc.SpriteFrame","content":{"name":"dice_24","texture":"4bNWVrT2hJm4pGB87KGOKP","rect":[1295,1035,185,185],"offset":[0,0],"originalSize":[185,185],"capInsets":[0,0,0,0]}},{"__type__":"cc.SpriteFrame","content":{"name":"dice_04","texture":"4bNWVrT2hJm4pGB87KGOKP","rect":[370,665,185,185],"offset":[0,0],"originalSize":[185,185],"capInsets":[0,0,0,0]}},{"__type__":"cc.SpriteFrame","content":{"name":"chan","texture":"4bNWVrT2hJm4pGB87KGOKP","rect":[1032,55,156,65],"offset":[0,0],"originalSize":[156,65],"capInsets":[0,0,0,0]}},{"__type__":"cc.SpriteFrame","content":{"name":"dot_cr","texture":"4bNWVrT2hJm4pGB87KGOKP","rect":[0,0,22,22],"offset":[0,0],"originalSize":[22,22],"capInsets":[0,0,0,0]}},{"__type__":"cc.SpriteFrame","content":{"name":"tai","texture":"4bNWVrT2hJm4pGB87KGOKP","rect":[1340,55,104,78],"offset":[0,0],"originalSize":[104,78],"capInsets":[0,0,0,0]}},{"__type__":"cc.SpriteFrame","content":{"name":"dice_28","texture":"4bNWVrT2hJm4pGB87KGOKP","rect":[370,850,185,185],"offset":[0,0],"originalSize":[185,185],"capInsets":[0,0,0,0]}},{"__type__":"cc.SpriteFrame","content":{"name":"dice_18","texture":"4bNWVrT2hJm4pGB87KGOKP","rect":[370,1035,185,185],"offset":[0,0],"originalSize":[185,185],"capInsets":[0,0,0,0]}},{"__type__":"cc.SpriteFrame","content":{"name":"dice_11","texture":"4bNWVrT2hJm4pGB87KGOKP","rect":[185,665,185,185],"offset":[0,0],"originalSize":[185,185],"capInsets":[0,0,0,0]}},{"__type__":"cc.SpriteFrame","content":{"name":"dice_09","texture":"4bNWVrT2hJm4pGB87KGOKP","rect":[1295,665,185,185],"offset":[0,0],"originalSize":[185,185],"capInsets":[0,0,0,0]}},{"__type__":"cc.SpriteFrame","content":{"name":"dice_26","texture":"4bNWVrT2hJm4pGB87KGOKP","rect":[740,850,185,185],"offset":[0,0],"originalSize":[185,185],"capInsets":[0,0,0,0]}},{"__type__":"cc.SpriteAtlas","_name":"TaiXiu.plist","_spriteFrames":{"bg-history":{"__uuid__":"180uBDe/tFS4VX1Nt8++d1"},"bg-text":{"__uuid__":"4ezVeO2MlJDaOY5xqdlErX"},"bg":{"__uuid__":"7b8Qm3vVZBn4hJbMH6yYS7"},"bg_number":{"__uuid__":"1depKBohpCPI7/NYgjruOy"},"bg_number2":{"__uuid__":"aef/WexVFIw7kxUHbWJ+xb"},"bg_number2_light":{"__uuid__":"b1gNtVzL5F75UY011A4JVh"},"bg_number_light":{"__uuid__":"5bKgothE1DgoEpeGriSvIQ"},"button-history":{"__uuid__":"7a9Dv2kxJEDY0Ww48/e93M"},"chan":{"__uuid__":"5ecKEbtx1Ko6rUsXssWl73"},"diaNan":{"__uuid__":"10jZ4qhx1LxpyRZ0QmG02m"},"dice_01":{"__uuid__":"85SN2ZQPZLl5QLaDz5IQvk"},"dice_02":{"__uuid__":"e2O9ru0XVCBIpu9Trnv/k5"},"dice_03":{"__uuid__":"3bLmD3oTtP2ZytsK3YRqNi"},"dice_04":{"__uuid__":"5eTs75pkZKrb8X4eQFhsKU"},"dice_05":{"__uuid__":"51DQ4XEK1Dh4XWI0VhoMol"},"dice_06":{"__uuid__":"92vbH2ZvlMqrH52viRIR9c"},"dice_07":{"__uuid__":"d3lupDj3hLy5rHmB70/NjD"},"dice_08":{"__uuid__":"31QAQJeiRD9bLUtQtcTtz4"},"dice_09":{"__uuid__":"77E0gYqF5DSrJMe4XJ6hVr"},"dice_10":{"__uuid__":"36ZTBUv81O4pxCpKrJ5bjY"},"dice_11":{"__uuid__":"71cXkdXPFKlpp79Mk8HY3U"},"dice_12":{"__uuid__":"b5wB9ttjVELpO26pMc3DEg"},"dice_13":{"__uuid__":"8b30+wylRFCb6fIuOVpXvw"},"dice_14":{"__uuid__":"3e64feJaRFp7Yb1JaR5g4p"},"dice_15":{"__uuid__":"50IkLKfx5MXqMCGIGSA2nw"},"dice_16":{"__uuid__":"54cgGTZdBL6oTlaWv2yKdl"},"dice_17":{"__uuid__":"5eAFTfJw1BE5wamEah5sCL"},"dice_18":{"__uuid__":"6bEVlPdnBBurfOXimMJCBg"},"dice_19":{"__uuid__":"a2e2klHGxDHqBTFhFt7JEW"},"dice_20":{"__uuid__":"adT6nApMNJHpimAxHM9ioF"},"dice_21":{"__uuid__":"b63t5K2RtJErstK418qK9q"},"dice_22":{"__uuid__":"2ekL/Y1sxOGbeReB3zsWgI"},"dice_23":{"__uuid__":"e1rCzNXn5GOq5ZUMTzlBN+"},"dice_24":{"__uuid__":"5eQLytTZ1AtJQPCZ5Sfzta"},"dice_25":{"__uuid__":"84SgzJm5BOC7foqsg/og3j"},"dice_26":{"__uuid__":"78TSPV/qpIeLmhLboZwuxR"},"dice_27":{"__uuid__":"9e1DzKn9dIsLyk9kKXYZXr"},"dice_28":{"__uuid__":"6aJJ0m7FJB4aKBHECvaUIZ"},"dice_29":{"__uuid__":"4fH/oSxzVE0bYb7hrBg0kr"},"dice_30":{"__uuid__":"abXVMSlZpNHKUwJVBi743b"},"dice_31":{"__uuid__":"c84fMqlvNO2ZMPnq0psl6z"},"dice_32":{"__uuid__":"45chm+RltCvas8qk6KORfD"},"dice_33":{"__uuid__":"b2hOK5hd9IXKEUYBbcQ+aO"},"dice_34":{"__uuid__":"a3+1xMc8pLn5RGjeRF8Mue"},"dice_35":{"__uuid__":"371LX1goxC8IbsO7GTs/8M"},"dice_36":{"__uuid__":"d2aXPo0NVEKoj6xm/Sxu7k"},"dice_37":{"__uuid__":"d0ktnJJipIzIhXx+k9seVC"},"dice_38":{"__uuid__":"aa9Pw9QDxBtp8wiHDb2gPK"},"dice_39":{"__uuid__":"5cWNsAv8pEv6/F0arxQCZs"},"dot":{"__uuid__":"3ei5xxaahKPIyzajUg/CLR"},"dot_black":{"__uuid__":"b7FZx5zxFKMpA70Dy5jOXE"},"dot_cr":{"__uuid__":"60nz1yofVE1qJdmVxxxaks"},"dot_white":{"__uuid__":"59tR6ua9ZMKpE95lFnXa+C"},"dot_yellow":{"__uuid__":"ddsAGgr1pA24JWrUioinTh"},"le":{"__uuid__":"0bHGVhKndIKKMw5oB9ooQJ"},"p-1":{"__uuid__":"19w8XiMGdH5ajAviVobb8S"},"p-2":{"__uuid__":"84bUXrbsNLPoBj7gk+PPVL"},"p-3":{"__uuid__":"00yS3+hpJGQoBfav24eRlL"},"p-4":{"__uuid__":"2cbZdo+qBBLL5z5H9lpWwh"},"p-5":{"__uuid__":"16psB4oN9BnINKzceJ3L/m"},"p-6":{"__uuid__":"b4F7M9audL1ofR317LEzPR"},"table-chart1":{"__uuid__":"f4NcQOUkdJY5Qe0vsVfdzn"},"table-chart2":{"__uuid__":"a5FLO1XJ5BkZhbRH5w+23R"},"table-result":{"__uuid__":"deJmpYaVNGVpYpGibxidjT"},"tai-xiu-bet-bg-2":{"__uuid__":"5dqMIKjOBGw4xOIviIAVdw"},"tai-xiu-bet-bg":{"__uuid__":"edmWgRhfpEwr/Gh7VrOX5P"},"tai-xiu-bg-2":{"__uuid__":"0c2ObpaZJGB6AajwCsrJCl"},"tai-xiu-button-nan-off":{"__uuid__":"39ooXQtrtHXbtoSq4KM7gM"},"tai-xiu-button-nan":{"__uuid__":"c5k6e/0EZGXp1pzwXp8DvH"},"tai-xiu-chain-bg":{"__uuid__":"c1sXShfDxEgIEwfYti3GsS"},"tai-xiu-chat-bg":{"__uuid__":"f3jFh2QXRHGKsV0d3fazTD"},"tai-xiu-history-bg":{"__uuid__":"c9m1qxscVLdb4vJ8hkrlCZ"},"tai-xiu-layer-2":{"__uuid__":"d0fjoR/VtKI7xpwtJi2QrS"},"tai-xiu-layer-3":{"__uuid__":"c33hI0ln1KTpz6Bor+yhMe"},"tai-xiu-layer-4":{"__uuid__":"7aW1GlNXhE17EwAkgCdhDi"},"tai":{"__uuid__":"68ufoYZl1EgbJWqLC9IRcg"},"thongke_tong":{"__uuid__":"48HHgk4vRCophKcnXGTas3"},"thongke_xucxac1":{"__uuid__":"55c6SKLZlD/IvlpEmP+WK9"},"thongke_xucxac2":{"__uuid__":"2e/n2vvxlO0K+thLridxMu"},"thongke_xucxac3":{"__uuid__":"b6cXFiUSpE64ZJzwn4arIS"},"time_line":{"__uuid__":"d9SazZtyRN7LdyXvVYbN2V"},"tip":{"__uuid__":"095VHeaCpKcLF2a5hLbRgb"},"title-result":{"__uuid__":"f0Rr3xgntIGYfZcIWgwt+9"},"title":{"__uuid__":"f9CzroS8hP/q35/EmCqE+N"},"user":{"__uuid__":"d034JjTWRLI7mcSjdNKohT"},"xiu":{"__uuid__":"25FeyXtfJBFLtC+bBABD3O"}}},{"__type__":"cc.SpriteFrame","content":{"name":"tai-xiu-layer-4","texture":"4bNWVrT2hJm4pGB87KGOKP","rect":[1475,1220,288,288],"offset":[0,0],"originalSize":[288,288],"capInsets":[0,0,0,0]}},{"__type__":"cc.SpriteFrame","content":{"name":"button-history","texture":"4bNWVrT2hJm4pGB87KGOKP","rect":[1522,55,78,82],"offset":[0,0],"originalSize":[78,82],"capInsets":[0,0,0,0]}},{"__type__":"cc.SpriteFrame","content":{"name":"bg","texture":"4bNWVrT2hJm4pGB87KGOKP","rect":[1026,1508,815,442],"offset":[0,0],"originalSize":[815,442],"capInsets":[0,0,0,0]}},{"__type__":"cc.SpriteFrame","content":{"name":"dice_25","texture":"4bNWVrT2hJm4pGB87KGOKP","rect":[1110,1035,185,185],"offset":[0,0],"originalSize":[185,185],"capInsets":[0,0,0,0]}},{"__type__":"cc.SpriteFrame","content":{"name":"p-2","texture":"4bNWVrT2hJm4pGB87KGOKP","rect":[1362,0,51,52],"offset":[0,0],"originalSize":[51,52],"capInsets":[0,0,0,0]}},{"__type__":"cc.SpriteFrame","content":{"name":"dice_01","texture":"4bNWVrT2hJm4pGB87KGOKP","rect":[1295,480,185,185],"offset":[0,0],"originalSize":[185,185],"capInsets":[0,0,0,0]}},{"__type__":"cc.SpriteFrame","content":{"name":"dice_13","texture":"4bNWVrT2hJm4pGB87KGOKP","rect":[1110,480,185,185],"offset":[0,0],"originalSize":[185,185],"capInsets":[0,0,0,0]}},{"__type__":"cc.SpriteFrame","content":{"name":"dice_06","texture":"4bNWVrT2hJm4pGB87KGOKP","rect":[925,665,185,185],"offset":[0,0],"originalSize":[185,185],"capInsets":[0,0,0,0]}},{"__type__":"cc.SpriteFrame","content":{"name":"dice_27","texture":"4bNWVrT2hJm4pGB87KGOKP","rect":[185,1035,185,185],"offset":[0,0],"originalSize":[185,185],"capInsets":[0,0,0,0]}},{"__type__":"cc.SpriteFrame","content":{"name":"dice_19","texture":"4bNWVrT2hJm4pGB87KGOKP","rect":[555,1035,185,185],"offset":[0,0],"originalSize":[185,185],"capInsets":[0,0,0,0]}},{"__type__":"cc.SpriteFrame","content":{"name":"dice_34","texture":"4bNWVrT2hJm4pGB87KGOKP","rect":[370,480,185,185],"offset":[0,0],"originalSize":[185,185],"capInsets":[0,0,0,0]}},{"__type__":"cc.SpriteFrame","content":{"name":"table-chart2","texture":"4bNWVrT2hJm4pGB87KGOKP","rect":[585,295,602,182],"offset":[0,0],"originalSize":[602,182],"capInsets":[0,0,0,0]}},{"__type__":"cc.SpriteFrame","content":{"name":"dice_38","texture":"4bNWVrT2hJm4pGB87KGOKP","rect":[1556,295,185,185],"offset":[0,0],"originalSize":[185,185],"capInsets":[0,0,0,0]}},{"__type__":"cc.SpriteFrame","content":{"name":"dice_30","texture":"4bNWVrT2hJm4pGB87KGOKP","rect":[925,850,185,185],"offset":[0,0],"originalSize":[185,185],"capInsets":[0,0,0,0]}},{"__type__":"cc.SpriteFrame","content":{"name":"dice_20","texture":"4bNWVrT2hJm4pGB87KGOKP","rect":[740,1035,185,185],"offset":[0,0],"originalSize":[185,185],"capInsets":[0,0,0,0]}},{"__type__":"cc.SpriteFrame","content":{"name":"bg_number2","texture":"4bNWVrT2hJm4pGB87KGOKP","rect":[0,55,74,55],"offset":[0,0],"originalSize":[74,55],"capInsets":[0,0,0,0]}},{"__type__":"cc.SpriteFrame","content":{"name":"bg_number2_light","texture":"4bNWVrT2hJm4pGB87KGOKP","rect":[74,55,74,55],"offset":[0,0],"originalSize":[74,55],"capInsets":[0,0,0,0]}},{"__type__":"cc.SpriteFrame","content":{"name":"dice_33","texture":"4bNWVrT2hJm4pGB87KGOKP","rect":[0,1035,185,185],"offset":[0,0],"originalSize":[185,185],"capInsets":[0,0,0,0]}},{"__type__":"cc.SpriteFrame","content":{"name":"p-6","texture":"4bNWVrT2hJm4pGB87KGOKP","rect":[1464,0,51,52],"offset":[0,0],"originalSize":[51,52],"capInsets":[0,0,0,0]}},{"__type__":"cc.SpriteFrame","content":{"name":"dice_12","texture":"4bNWVrT2hJm4pGB87KGOKP","rect":[740,480,185,185],"offset":[0,0],"originalSize":[185,185],"capInsets":[0,0,0,0]}},{"__type__":"cc.SpriteFrame","content":{"name":"thongke_xucxac3","texture":"4bNWVrT2hJm4pGB87KGOKP","rect":[75,0,27,27],"offset":[0,0],"originalSize":[27,27],"capInsets":[0,0,0,0]}},{"__type__":"cc.SpriteFrame","content":{"name":"dice_21","texture":"4bNWVrT2hJm4pGB87KGOKP","rect":[925,1035,185,185],"offset":[0,0],"originalSize":[185,185],"capInsets":[0,0,0,0]}},{"__type__":"cc.SpriteFrame","content":{"name":"dot_black","texture":"4bNWVrT2hJm4pGB87KGOKP","rect":[189,0,30,29],"offset":[0,0],"originalSize":[30,29],"capInsets":[0,0,0,0]}},{"__type__":"cc.SpriteFrame","content":{"name":"tai-xiu-chain-bg","texture":"4bNWVrT2hJm4pGB87KGOKP","rect":[0,140,516,104],"offset":[0,0],"originalSize":[516,104],"capInsets":[0,0,0,0]}},{"__type__":"cc.SpriteFrame","content":{"name":"tai-xiu-layer-3","texture":"4bNWVrT2hJm4pGB87KGOKP","rect":[1188,55,76,77],"offset":[0,0],"originalSize":[76,77],"capInsets":[0,0,0,0]}},{"__type__":"cc.SpriteFrame","content":{"name":"tai-xiu-button-nan","texture":"4bNWVrT2hJm4pGB87KGOKP","rect":[1444,55,78,82],"offset":[0,0],"originalSize":[78,82],"capInsets":[0,0,0,0]}},{"__type__":"cc.SpriteFrame","content":{"name":"dice_31","texture":"4bNWVrT2hJm4pGB87KGOKP","rect":[1110,850,185,185],"offset":[0,0],"originalSize":[185,185],"capInsets":[0,0,0,0]}},{"__type__":"cc.SpriteFrame","content":{"name":"tai-xiu-history-bg","texture":"4bNWVrT2hJm4pGB87KGOKP","rect":[279,0,583,32],"offset":[0,0],"originalSize":[583,32],"capInsets":[0,0,0,0]}},{"__type__":"cc.SpriteFrame","content":{"name":"tai-xiu-layer-2","texture":"4bNWVrT2hJm4pGB87KGOKP","rect":[1264,55,76,77],"offset":[0,0],"originalSize":[76,77],"capInsets":[0,0,0,0]}},{"__type__":"cc.SpriteFrame","content":{"name":"dice_37","texture":"4bNWVrT2hJm4pGB87KGOKP","rect":[1371,295,185,185],"offset":[0,0],"originalSize":[185,185],"capInsets":[0,0,0,0]}},{"__type__":"cc.SpriteFrame","content":{"name":"user","texture":"4bNWVrT2hJm4pGB87KGOKP","rect":[156,0,33,28],"offset":[0,0],"originalSize":[33,28],"capInsets":[0,0,0,0]}},{"__type__":"cc.SpriteFrame","content":{"name":"dice_36","texture":"4bNWVrT2hJm4pGB87KGOKP","rect":[185,480,185,185],"offset":[0,0],"originalSize":[185,185],"capInsets":[0,0,0,0]}},{"__type__":"cc.SpriteFrame","content":{"name":"dice_07","texture":"4bNWVrT2hJm4pGB87KGOKP","rect":[1110,665,185,185],"offset":[0,0],"originalSize":[185,185],"capInsets":[0,0,0,0]}},{"__type__":"cc.SpriteFrame","content":{"name":"time_line","texture":"4bNWVrT2hJm4pGB87KGOKP","rect":[185,1220,574,190],"offset":[0,0],"originalSize":[574,190],"capInsets":[0,0,0,0]}},{"__type__":"cc.SpriteFrame","content":{"name":"dot_yellow","texture":"4bNWVrT2hJm4pGB87KGOKP","rect":[219,0,30,29],"offset":[0,0],"originalSize":[30,29],"capInsets":[0,0,0,0]}},{"__type__":"cc.SpriteFrame","content":{"name":"table-result","texture":"4bNWVrT2hJm4pGB87KGOKP","rect":[1028,140,617,155],"offset":[0,0],"originalSize":[617,155],"capInsets":[0,0,0,0]}},{"__type__":"cc.SpriteFrame","content":{"name":"dice_23","texture":"4bNWVrT2hJm4pGB87KGOKP","rect":[1480,1035,185,185],"offset":[0,0],"originalSize":[185,185],"capInsets":[0,0,0,0]}},{"__type__":"cc.SpriteFrame","content":{"name":"dice_02","texture":"4bNWVrT2hJm4pGB87KGOKP","rect":[555,480,185,185],"offset":[0,0],"originalSize":[185,185],"capInsets":[0,0,0,0]}},{"__type__":"cc.SpriteFrame","content":{"name":"tai-xiu-bet-bg","texture":"4bNWVrT2hJm4pGB87KGOKP","rect":[148,55,230,60],"offset":[0,0],"originalSize":[230,60],"capInsets":[0,0,0,0]}},{"__type__":"cc.SpriteFrame","content":{"name":"title-result","texture":"4bNWVrT2hJm4pGB87KGOKP","rect":[608,55,359,60],"offset":[0,0],"originalSize":[359,60],"capInsets":[0,0,0,0]}},{"__type__":"cc.SpriteFrame","content":{"name":"tai-xiu-chat-bg","texture":"4bNWVrT2hJm4pGB87KGOKP","rect":[0,1508,340,402],"offset":[0,0],"originalSize":[340,402],"capInsets":[0,0,0,0]}},{"__type__":"cc.SpriteFrame","content":{"name":"table-chart1","texture":"4bNWVrT2hJm4pGB87KGOKP","rect":[0,295,585,162],"offset":[0,0],"originalSize":[585,162],"capInsets":[0,0,0,0]}},{"__type__":"cc.SpriteFrame","content":{"name":"title","texture":"4bNWVrT2hJm4pGB87KGOKP","rect":[516,140,512,137],"offset":[0,0],"originalSize":[512,137],"capInsets":[0,0,0,0]}}]